low_rank_toolbox-1.0.1.dist-info/licenses/LICENSE
lowrank/__init__.py
lowrank/cssp/__init__.py
lowrank/cssp/arp.py
lowrank/cssp/deim.py
lowrank/cssp/gpode.py
lowrank/cssp/gpodr.py
lowrank/cssp/osinsky.py
lowrank/cssp/oversampling_sqdeim.py
lowrank/cssp/qdeim.py
lowrank/cssp/sqdeim.py
lowrank/cssp/utils/__init__.py
lowrank/cssp/utils/givens.py
lowrank/cssp/utils/sRRQR.py
lowrank/krylov/__init__.py
lowrank/krylov/data/__init__.py
lowrank/krylov/data/optimal_poles.py
lowrank/krylov/solvers/__init__.py
lowrank/krylov/solvers/lyapunov_solvers.py
lowrank/krylov/solvers/sylvester_solvers.py
lowrank/krylov/spaces/__init__.py
lowrank/krylov/spaces/extended_krylov_space.py
lowrank/krylov/spaces/inverted_krylov_space.py
lowrank/krylov/spaces/krylov_space.py
lowrank/krylov/spaces/rational_krylov_space.py
lowrank/krylov/spaces/space_structure.py
lowrank/krylov/utils/__init__.py
lowrank/krylov/utils/arnoldi.py
lowrank/krylov/utils/lanczos.py
lowrank/matrices/__init__.py
lowrank/matrices/_qr_config.py
lowrank/matrices/_svd_config.py
lowrank/matrices/low_rank_matrix.py
lowrank/matrices/qr.py
lowrank/matrices/quasi_svd.py
lowrank/matrices/svd.py
lowrank/randomized/__init__.py
lowrank/randomized/generalized_nystrom.py
lowrank/randomized/randomized_svd.py
lowrank/randomized/rangefinder.py
low_rank_toolbox-1.0.1.dist-info/METADATA
low_rank_toolbox-1.0.1.dist-info/WHEEL
low_rank_toolbox-1.0.1.dist-info/top_level.txt
low_rank_toolbox-1.0.1.dist-info/RECORD
