Metadata-Version: 2.4
Name: low-rank-toolbox
Version: 1.0.1
Summary: A Python library for efficient low-rank matrix and tensor operations.
Author-email: Benjamin Carrel <benjamin.carrel@psi.ch>
License-Expression: MIT
Project-URL: Homepage, https://github.com/BenjaminCarrel/low-rank-toolbox
Project-URL: Bug Tracker, https://github.com/BenjaminCarrel/low-rank-toolbox/issues
Classifier: Programming Language :: Python :: 3
Classifier: Operating System :: OS Independent
Classifier: Intended Audience :: Science/Research
Classifier: Topic :: Scientific/Engineering :: Mathematics
Requires-Python: >=3.10
License-File: LICENSE
Requires-Dist: numpy>=1.21
Requires-Dist: scipy>=1.7
Dynamic: license-file
